{
  "name": "ngiger-cockpit",
  "version": "0.1.0",
  "author": "Niklaus Giger <niklaus.giger@member.fsf.org>",
  "summary": "Puppet module for Elexis cockpit ",
  "license": "GNU General Public License v3 or Later (GPLv3+)",
  "source": "",
  "project_page": "https://github.com/ngiger/puppet-cockpit",
  "issues_url": null,
  "description": "Puppet module for Elexis cockpit. Wartungsarbeiten für Anwender von Elexis.\ns.a https://github.com/elexis/elexis-cockpit/. Only tested under Debian.",
  "dependencies": [
    {"name":"jdowning/rbenv","version_requirement":">= 1.3"},
    {"name":"puppetlabs/vcsrepo","version_requirement":">= 1.0.0"},
    {"name":"puppetlabs/apt","version_requirement":">= 1.0.0"},
    {"name":"jbussdieker/daemontools","version_requirement":">= 0.0.3"}
  ]
}
